applitools/images/__init__.py
applitools/images/__version__.py
applitools/images/extract_text.py
applitools/images/eyes.py
applitools/images/fluent.py
applitools/images/protocol.py
applitools/images/py.typed
applitools/images/runner.py
eyes_images-6.3.18.dist-info/licenses/LICENSE
eyes_images-6.3.18.dist-info/METADATA
eyes_images-6.3.18.dist-info/WHEEL
eyes_images-6.3.18.dist-info/top_level.txt
eyes_images-6.3.18.dist-info/RECORD
