Metadata-Version: 2.4
Name: eyes-images
Version: 6.3.18
Summary: Applitools Python SDK. Images package
Author-email: Applitools Team <team@applitools.com>
License-Expression: LicenseRef-Proprietary
Project-URL: Homepage, https://applitools.com
Keywords: applitools,eyes
Classifier: Programming Language :: Python
Classifier: Development Status :: 5 - Production/Stable
Classifier: Intended Audience :: Developers
Classifier: Operating System :: MacOS
Classifier: Operating System :: Microsoft :: Windows
Classifier: Operating System :: POSIX :: Linux
Classifier: Topic :: Software Development :: Quality Assurance
Classifier: Topic :: Software Development :: Testing
Requires-Python: <4,>=3.7
License-File: LICENSE
Requires-Dist: eyes-common==6.5.18
Dynamic: license-file
